Workbook

Sheet Contents
B2: Preckon — platform report and test plan
B3: Live system as at 27 August 2026. Prepared 28 August 2026.
B6: PART 1 | C6: What the system shows today
B7: Executive summary | C7: The story in one page, and what we are asking for | D7: Report
B8: Stage by stage | C8: How each step of the bid performed, with timing | D8: Report
B9: Tokens & cost by step | C9: Tokens in, out and cost for all 17 steps | D9: Report
B10: Tokens & cost by project | C10: The same, charged to each of the six projects | D10: Report
B11: Where work is stuck | C11: The approval queue — 1,367 items waiting | D11: Report
B12: Cost scaling | C12: Editable scenarios for what a year would cost | D12: Report
B13: Issues & actions | C13: Seven items, prioritised, with owner and date to fill in | D13: Report
B14: PART 2 | C14: The plan to test it properly
B15: Test progress | C15: Rolls up from the five test sheets as they are filled in | D15: Test
B16: Test · Functional | C16: 40 cases across all modules and the platform | D16: Test
B17: Test · Documents | C17: 15 runs — processing time and tokens by file size | D17: Test
B18: Test · Drawings | C18: 12 runs — simple, medium, complex and scanned | D18: Test
B19: Test · Tokens | C19: All 17 steps, and the total for one full bid | D19: Test
B20: Test · Accuracy | C20: 10 extraction types, with precision and recall | D20: Test
B21: PART 3 | C21: Reference
B22: Targets | C22: Every threshold, with today's figure beside it | D22: Reference
B23: Test data needed | C23: The files to prepare before testing can start | D23: Reference
B24: Glossary | C24: Plain definitions for every term used | D24: Reference
B26: Colour key
B27: Cream | C27: You fill this in.
B28: Grey | C28: Calculates itself — do not type over it.
B29: Red | C29: Needs a decision or is not working.
B30: Amber | C30: Works, but worth watching.
B31: Green | C31: Working.

Sheet Executive summary
B3: The numbers
B5: Jobs run | C5: 228 | D5: Across six projects.
B6: AI requests | C6: 88 | D6: Across 14 active steps.
B7: Blocked by privacy rule | C7: 44 | D7: Refused before reaching the AI. Cost nothing.
B8: Total tokens | C8: 26040 | D8: See the caveat below.
B9: Total cost | C9: 3.36 | D9: Arithmetic on a placeholder. Not spend.
B10: Waiting for approval | C10: 1367 | D10: This is where work is stopping.
B11: Actually approved | C11: 8 | D11: Out of 1,367. None rejected either.
B12: Repeat work reused | C12: 0 | D12: The reuse feature is switched off.
B13: System errors | C13: 2 | D13: In pricing and procurement.
B15: Before the cost figure is used for anything
B16: Every successful request records the same fixed usage — 250 tokens in, 60 out — no matter what it was given. A 0.2 MB document and a 33 MB document both record 310 tokens. The breakdown by step and project is shaped correctly, but the absolute dollars are not real spend.
B18: What we are asking for
B19: • A decision on the data-classification policy, so ordinary tender documents can be processed by the AI.
B20: • An owner for the approval queue — 1,367 items are waiting on a person.
B21: • Sign-off on the test plan in Part 2, and the targets that go with it.

Sheet Stage by stage
A1: ‹ Contents
A3: # | B3: Step | C3: What it does | D3: Requests | E3: Blocked | F3: Errors | G3: Typical time | H3: Queue wait | I3: Status | J3: What to read into it
A4: 1 | B4: Reading documents | C4: Sorts and splits the uploaded tender pack | D4: 30 | E4: 15 | F4: 0 | G4: 4 sec | H4: — | I4: Working
A5: 2 | B5: Tender reading | C5: Pulls summary, dates and requirements | D5: 6 | E5: 3 | F5: 0 | G5: 4 min | H5: 5 hrs | I5: Action | J5: Waits far longer than it takes to run.
A6: 3 | B6: Bid / no-bid decision | C6: Recommends whether to pursue | D6: 2 | E6: 1 | F6: 0 | G6: 6 min | H6: — | I6: Action | J6: Slow enough that a person would notice.
A7: 4 | B7: Specification reading | C7: Extracts clauses from the specification | D7: 2 | E7: 1 | F7: 0 | G7: 2 sec | H7: — | I7: Working
A8: 5 | B8: Drawing indexing | C8: Catalogues each drawing sheet | D8: 0 | E8: 0 | F8: 0 | G8: — | H8: — | I8: Blocked | J8: Never ran. Nothing produced at all.
A9: 6 | B9: Drawing take-off | C9: Measures quantities off the drawings | D9: 0 | E9: 0 | F9: 0 | G9: — | H9: — | I9: Blocked | J9: Never ran. Nothing produced at all.
A10: 7 | B10: Bill of quantities | C10: Turns measurements into bill lines | D10: 6 | E10: 3 | F10: 0 | G10: 2 min | H10: — | I10: Working
A11: 8 | B11: Pricing | C11: Applies rates to the bill lines | D11: 4 | E11: 2 | F11: 1 | G11: 5 min | H11: 4 hrs | I11: Action | J11: Waits far longer than it takes to run.
A12: 9 | B12: Compliance checks | C12: Checks the bid against requirements | D12: 6 | E12: 3 | F12: 0 | G12: 2 sec | H12: 5 hrs | I12: Action | J12: Waits far longer than it takes to run.
A13: 10 | B13: Risk assessment | C13: Flags risks on the bid | D13: 4 | E13: 2 | F13: 0 | G13: 10 sec | H13: — | I13: Working
A14: 11 | B14: Programme / schedule | C14: Builds the works programme | D14: 2 | E14: 1 | F14: 0 | G14: 16 sec | H14: 37 hrs | I14: Action | J14: Waits far longer than it takes to run.
A15: 12 | B15: Procurement packages | C15: Groups bill lines into packages | D15: 2 | E15: 1 | F15: 1 | G15: 8 sec | H15: 26 hrs | I15: Action | J15: Waits far longer than it takes to run.
A16: 13 | B16: Technical narrative | C16: Writes the technical submission | D16: 0 | E16: 0 | F16: 0 | G16: — | H16: — | I16: Blocked | J16: Never ran. Nothing produced at all.
A17: 14 | B17: Proposal writing | C17: Drafts the proposal document | D17: 6 | E17: 3 | F17: 0 | G17: 1 sec | H17: — | I17: Working
A18: 15 | B18: Bid approval pack | C18: Assembles the approval pack | D18: 6 | E18: 3 | F18: 0 | G18: 2 sec | H18: — | I18: Working
A19: 16 | B19: Client clarifications | C19: Drafts questions back to the client | D19: 2 | E19: 1 | F19: 0 | G19: 10 sec | H19: — | I19: Working
A20: 17 | B20: Copilot answers | C20: Answers questions people ask | D20: 10 | E20: 5 | F20: 0 | G20: 4 sec | H20: — | I20: Working

Sheet Tokens & cost by step
A1: ‹ Contents
A3: # | B3: Step | C3: Requests | D3: Blocked | E3: Errors | F3: Tokens in | G3: Tokens out | H3: Total tokens | I3: Cost | J3: Cost / request | K3: % of cost | L3: Running cost
A4: 1 | B4: Reading documents | C4: 30 | D4: 15 | E4: 0 | F4: 7500 | G4: 1800 | H4: 9300 | I4: 1.2 | J4: 0.04 | K4: 0.35714286 | L4: 1.2
A5: 2 | B5: Tender reading | C5: 6 | D5: 3 | E5: 0 | F5: 1500 | G5: 360 | H5: 1860 | I5: 0.24 | J5: 0.04 | K5: 0.071428571 | L5: 1.44
A6: 3 | B6: Bid / no-bid decision | C6: 2 | D6: 1 | E6: 0 | F6: 500 | G6: 120 | H6: 620 | I6: 0.08 | J6: 0.04 | K6: 0.023809524 | L6: 1.52
A7: 4 | B7: Specification reading | C7: 2 | D7: 1 | E7: 0 | F7: 500 | G7: 120 | H7: 620 | I7: 0.08 | J7: 0.04 | K7: 0.023809524 | L7: 1.6
A8: 5 | B8: Drawing indexing | C8: 0 | D8: 0 | E8: 0 | F8: 0 | G8: 0 | H8: 0 | I8: 0 | J8: 0 | K8: 0 | L8: 1.6
A9: 6 | B9: Drawing take-off | C9: 0 | D9: 0 | E9: 0 | F9: 0 | G9: 0 | H9: 0 | I9: 0 | J9: 0 | K9: 0 | L9: 1.6
A10: 7 | B10: Bill of quantities | C10: 6 | D10: 3 | E10: 0 | F10: 1500 | G10: 360 | H10: 1860 | I10: 0.24 | J10: 0.04 | K10: 0.071428571 | L10: 1.84
A11: 8 | B11: Pricing | C11: 4 | D11: 2 | E11: 1 | F11: 500 | G11: 120 | H11: 620 | I11: 0.08 | J11: 0.02 | K11: 0.023809524 | L11: 1.92
A12: 9 | B12: Compliance checks | C12: 6 | D12: 3 | E12: 0 | F12: 1500 | G12: 360 | H12: 1860 | I12: 0.24 | J12: 0.04 | K12: 0.071428571 | L12: 2.16
A13: 10 | B13: Risk assessment | C13: 4 | D13: 2 | E13: 0 | F13: 1000 | G13: 240 | H13: 1240 | I13: 0.16 | J13: 0.04 | K13: 0.047619048 | L13: 2.32
A14: 11 | B14: Programme / schedule | C14: 2 | D14: 1 | E14: 0 | F14: 500 | G14: 120 | H14: 620 | I14: 0.08 | J14: 0.04 | K14: 0.023809524 | L14: 2.4
A15: 12 | B15: Procurement packages | C15: 2 | D15: 1 | E15: 1 | F15: 0 | G15: 0 | H15: 0 | I15: 0 | J15: 0 | K15: 0 | L15: 2.4
... A20: 17 | B20: Copilot answers | C20: 10 | D20: 5 | E20: 0 | F20: 2500 | G20: 600 | H20: 3100 | I20: 0.4 | J20: 0.04 | K20: 0.11904762 | L20: 3.36
B21: TOTAL | C21: 88 | D21: 44 | E21: 2 | F21: 21000 | G21: 5040 | H21: 26040 | I21: 3.36 | J21: 0.038181818 | K21: 1 | L21: 3.36
A23: Reading documents is 36% of all cost on its own — it runs once per uploaded file, so it scales with the size of the tender pack rather than the number of bids. Blocked requests cost nothing, so the true cost per completed request is roughly double the column shown. Blended rate: $0.1290 per 1,000 tokens.

Sheet Tokens & cost by project
A1: ‹ Contents
A2: Tokens and cost — by project
A3: Every request charged to the project that raised it.
A5: Project | B5: Requests | C5: Tokens in | D5: Tokens out | E5: Total tokens | F5: Cost | G5: Cost / request | H5: % of cost | I5: Errors | J5: Note
A6: DV Quaters | B6: 22 | C6: 5500 | D6: 1320 | E6: 6820 | F6: 0.88 | G6: 0.04 | H6: 0.26190476 | I6: 0
A7: DV Quaters Demo | B7: 20 | C7: 5000 | D7: 1200 | E7: 6200 | F7: 0.8 | G7: 0.04 | H7: 0.23809524 | I7: 0
A8: venkat1 | B8: 18 | C8: 4500 | D8: 1080 | E8: 5580 | F8: 0.72 | G8: 0.04 | H8: 0.21428571 | I8: 0
A9: Sowbelly Gulch Project | B9: 18 | C9: 3500 | D9: 840 | E9: 4340 | F9: 0.56 | G9: 0.031111111 | H9: 0.16666667 | I9: 2 | J9: Both system errors here — and it carries the real drawings.
A10: venkat02 | B10: 8 | C10: 2000 | D10: 480 | E10: 2480 | F10: 0.32 | G10: 0.04 | H10: 0.095238095 | I10: 0
A11: Shruthi2 | B11: 2 | C11: 500 | D11: 120 | E11: 620 | F11: 0.08 | G11: 0.04 | H11: 0.023809524 | I11: 0
A12: TOTAL | B12: 88 | C12: 21000 | D12: 5040 | E12: 26040 | F12: 3.36 | G12: 0.038181818 | H12: 1 | I12: 2
A14: Four of the six are test or demo projects. Cost per request is almost identical across all six — another way of seeing that usage is recorded as a fixed number rather than measured.

Sheet Where work is stuck
A1: ‹ Contents
A2: Where work is stuck
A5: What is waiting | B5: Waiting | C5: Approved | D5: Approved % | E5: Note
A6: Bill of quantity lines | B6: 796 | C6: 1 | D6: 0.0012562814 | E6: Biggest queue in the system.
A7: Priced lines | B7: 254 | C7: 0 | D7: 0 | E7: Nothing decided either way.
A8: Drawing measurements | B8: 76 | C8: 0 | D8: 0 | E8: Nothing decided either way.
A9: Specification clauses | B9: 65 | C9: 0 | D9: 0 | E9: Nothing decided either way.
A10: Programme activities | B10: 63 | C10: 0 | D10: 0 | E10: Nothing decided either way.
A11: Risks | B11: 44 | C11: 0 | D11: 0 | E11: Nothing decided either way.
A12: Procurement packages | B12: 18 | C12: 1 | D12: 0.055555556
A13: Compliance items | B13: 12 | C13: 0 | D13: 0 | E13: Nothing decided either way.
A14: Tender summaries | B14: 11 | C14: 0 | D14: 0 | E14: Nothing decided either way.
A15: Drawing indexes | B15: 10 | C15: 0 | D15: 0 | E15: Nothing decided either way.
A16: Proposal documents | B16: 6 | C16: 3 | D16: 0.5 | E16: Being worked.
A17: Bid approvals | B17: 6 | C17: 3 | D17: 0.5 | E17: Being worked.
A18: Bid decisions | B18: 3 | C18: 0 | D18: 0 | E18: Nothing decided either way.
A19: Client queries | B19: 3 | C19: 0 | D19: 0 | E19: Nothing decided either way.
A20: TOTAL | B20: 1367 | C20: 8 | D20: 0.0058522312
A22: Why this matters more than anything else here
A23: Everything upstream is producing work. Nothing downstream is moving. That nothing has been rejected either suggests an unworked queue rather than people refusing the output — worth confirming before it is read as a quality signal.

Sheet Cost scaling
A1: ‹ Contents
A2: What this scales to
A3: Straight arithmetic. Change the cream cells and the rest follows.
A5: Assumptions — edit these
A6: Cost per project, as measured | B6: 0.56
A7: Projects per year | B7: 40
A8: Uplift once usage is measured | B8: 10 | C8: x
A10: Result
A11: Scenario | B11: Per project | D11: Per year | E11: What it assumes
A12: As measured today | B12: =B6 -> 0.56 | D12: =B6*B7 -> 22.4 | E12: The placeholder usage figure, unchanged.
A13: With usage measured properly | B13: =B6*B8 -> 5.6 | D13: =B6*B8*B7 -> 224 | E13: Assumes real documents use the uplift above. A guess until the counter is fixed.
A14: If blocked requests also ran | B14: =B6*B8*2 -> 11.2 | D14: =B6*B8*2*B7 -> 448 | E14: Half of all requests are currently refused and cost nothing.
A16: Rows two and three are scenarios, not forecasts. Until the usage counter records what a request actually consumed, nobody can put a defensible number on what a real bid costs to run.

Sheet Issues & actions
A1: ‹ Contents
A3: # | B3: Issue | C3: What it means | D3: Priority | E3: Suggested next step | F3: Owner | G3: By when | H3: Status
A4: 1 | B4: Nobody is approving what the system produces | C4: 1,367 items waiting, 8 approved, none rejected. Until that queue is worked, nothing the platform produces turns into a bid. | D4: High | E4: Find out whether this is staffing, training, or a screen people cannot find. | H4: Not started
A5: 2 | B5: Half the AI requests are blocked by our own privacy rule | C5: 44 of 88 refused before reaching the AI. Anything unclassified is treated as confidential and cannot leave our servers. Correct behaviour, but it means the AI is barely exercised. | D5: High | E5: Decide the data-classification policy for ordinary tender documents. | H5: Not started
A6: 3 | B6: The cost and usage figures are not real | C6: Every request records the same fixed usage regardless of the document. The cost total is arithmetic on that constant. | D6: High | E6: Do not budget from these figures. The engineering fix is one line per call site. | H6: Not started
A7: 4 | B7: Three stages never ran at all | C7: Drawing take-off, drawing indexing and the technical narrative record zero activity on every attempt. Drawing measurements cannot be produced right now. | D7: High | E7: Confirm whether these are switched off or failing silently. | H7: Not started
A8: 5 | B8: Some jobs sit in a queue for hours | C8: Programme jobs wait 37 hours on average before starting, procurement 26. The work itself takes seconds. | D8: Medium | E8: Check whether the queue worker is keeping up or stalling. | H8: Not started
A9: 6 | B9: Repeat work is not being reused | C9: The reuse feature is switched off, so every request starts from scratch. | D9: Medium | E9: Turn on the response cache. Known outstanding item. | H9: Not started
A10: 7 | B10: Three measurements are not being recorded | C10: How long each AI step took, how confident it was, and whether its output validated are all missing. | D10: Low | E10: Small change — the fields exist, they are simply not written. | H10: Not started

Sheet Test progress
A1: ‹ Contents
B4: Area | C4: Tests | D4: Pass | E4: Fail | F4: Blocked | G4: Not started | H4: % done | I4: Note
B5: Test · Functional | C5: =COUNTIF('Test · Functional'!$G$4:$G$198,"Pass")+COUNTIF('Test · Functional'!$G$4:$G$198,"Fail")+COUNTIF('Test · Functional'!$G$4:$G$198,"Blocked")+COUNTIF('Test · Functional'!$G$4:$G$198,"Not started")+COUNTIF('Test · Functional'!$G$4:$G$198,"N/A") -> 40 | D5: =COUNTIF('Test · Functional'!$G$4:$G$198,"Pass") -> 0 | E5: =COUNTIF('Test · Functional'!$G$4:$G$198,"Fail") -> 0 | F5: =COUNTIF('Test · Functional'!$G$4:$G$198,"Blocked") -> 0 | G5: =COUNTIF('Test · Functional'!$G$4:$G$198,"Not started") -> 40 | H5: =IF(C5=0,0,(D5+E5)/C5) -> 0
B6: Test · Documents | C6: =COUNTIF('Test · Documents'!$L$4:$L$198,"Pass")+COUNTIF('Test · Documents'!$L$4:$L$198,"Fail")+COUNTIF('Test · Documents'!$L$4:$L$198,"Blocked")+COUNTIF('Test · Documents'!$L$4:$L$198,"Not started")+COUNTIF('Test · Documents'!$L$4:$L$198,"N/A") -> 15 | D6: =COUNTIF('Test · Documents'!$L$4:$L$198,"Pass") -> 0 | E6: =COUNTIF('Test · Documents'!$L$4:$L$198,"Fail") -> 0 | F6: =COUNTIF('Test · Documents'!$L$4:$L$198,"Blocked") -> 0 | G6: =COUNTIF('Test · Documents'!$L$4:$L$198,"Not started") -> 15 | H6: =IF(C6=0,0,(D6+E6)/C6) -> 0
B7: Test · Drawings | C7: =COUNTIF('Test · Drawings'!$M$4:$M$198,"Pass")+COUNTIF('Test · Drawings'!$M$4:$M$198,"Fail")+COUNTIF('Test · Drawings'!$M$4:$M$198,"Blocked")+COUNTIF('Test · Drawings'!$M$4:$M$198,"Not started")+COUNTIF('Test · Drawings'!$M$4:$M$198,"N/A") -> 12 | D7: =COUNTIF('Test · Drawings'!$M$4:$M$198,"Pass") -> 0 | E7: =COUNTIF('Test · Drawings'!$M$4:$M$198,"Fail") -> 0 | F7: =COUNTIF('Test · Drawings'!$M$4:$M$198,"Blocked") -> 0 | G7: =COUNTIF('Test · Drawings'!$M$4:$M$198,"Not started") -> 12 | H7: =IF(C7=0,0,(D7+E7)/C7) -> 0
B8: Test · Tokens | C8: =COUNTIF('Test · Tokens'!$I$4:$I$198,"Pass")+COUNTIF('Test · Tokens'!$I$4:$I$198,"Fail")+COUNTIF('Test · Tokens'!$I$4:$I$198,"Blocked")+COUNTIF('Test · Tokens'!$I$4:$I$198,"Not started")+COUNTIF('Test · Tokens'!$I$4:$I$198,"N/A") -> 17 | D8: =COUNTIF('Test · Tokens'!$I$4:$I$198,"Pass") -> 0 | E8: =COUNTIF('Test · Tokens'!$I$4:$I$198,"Fail") -> 0 | F8: =COUNTIF('Test · Tokens'!$I$4:$I$198,"Blocked") -> 0 | G8: =COUNTIF('Test · Tokens'!$I$4:$I$198,"Not started") -> 17 | H8: =IF(C8=0,0,(D8+E8)/C8) -> 0
B9: Test · Accuracy | C9: =COUNTIF('Test · Accuracy'!$M$4:$M$198,"Pass")+COUNTIF('Test · Accuracy'!$M$4:$M$198,"Fail")+COUNTIF('Test · Accuracy'!$M$4:$M$198,"Blocked")+COUNTIF('Test · Accuracy'!$M$4:$M$198,"Not started")+COUNTIF('Test · Accuracy'!$M$4:$M$198,"N/A") -> 10 | D9: =COUNTIF('Test · Accuracy'!$M$4:$M$198,"Pass") -> 0 | E9: =COUNTIF('Test · Accuracy'!$M$4:$M$198,"Fail") -> 0 | F9: =COUNTIF('Test · Accuracy'!$M$4:$M$198,"Blocked") -> 0 | G9: =COUNTIF('Test · Accuracy'!$M$4:$M$198,"Not started") -> 10 | H9: =IF(C9=0,0,(D9+E9)/C9) -> 0
B10: TOTAL | C10: =SUM(C5:C9) -> 94 | D10: =SUM(D5:D9) -> 0 | E10: =SUM(E5:E9) -> 0 | F10: =SUM(F5:F9) -> 0 | G10: =SUM(G5:G9) -> 94 | H10: =IF(C10=0,0,(D10+E10)/C10) -> 0
B12: Sign-off
B13: Role | C13: Name | D13: Date | E13: Decision
B14: Test lead
B15: Engineering lead
B16: Product / manager

Sheet Test · Functional
A1: ‹ Contents
A3: ID | B3: Module | C3: Feature | D3: What to do | E3: What should happen | F3: Priority | G3: Result | H3: What actually happened | I3: Tester | J3: Date | K3: Notes / ticket
A4: TEN-01 | B4: TenderLogix | C4: Tender upload | D4: Upload a multi-file tender pack | E4: All files accepted, listed and queued | F4: High | G4: Not started
A5: TEN-02 | B5: TenderLogix | C5: Summary extraction | D5: Open the tender stage | E5: Client, reference, format and deadline all populated | F5: High | G5: Not started
A6: TEN-03 | B6: TenderLogix | C6: Requirements | D6: Check the requirement register | E6: Each requirement listed with its source clause | F6: High | G6: Not started
A7: TEN-04 | B7: TenderLogix | C7: Deadline override | D7: Change the deadline by hand | E7: Saved, and the change is on the audit trail | F7: Medium | G7: Not started
A8: TEN-05 | B8: TenderLogix | C8: Bid / no-bid | D8: Run bid qualification | E8: A recommendation with reasons, awaiting a decision | F8: Medium | G8: Not started
A9: DOC-01 | B9: DocLogix | C9: Register | D9: Upload 10 mixed documents | E9: All appear with type, revision and date | F9: High | G9: Not started
A10: DOC-02 | B10: DocLogix | C10: Revisions | D10: Upload a second revision | E10: Superseded kept, latest marked current | F10: High | G10: Not started
A11: DOC-03 | B11: DocLogix | C11: Transmittal | D11: Issue to two recipients | E11: Recorded with contents and recipients | F11: Medium | G11: Not started
A12: DOC-04 | B12: DocLogix | C12: Revision compare | D12: Compare two revisions | E12: Differences listed clearly | F12: Medium | G12: Not started
A13: DOC-05 | B13: DocLogix | C13: Search | D13: Search a phrase inside a document | E13: Document returned with the matching passage | F13: Medium | G13: Not started
A14: DRW-01 | B14: DrawLogix | C14: Upload PDF | D14: Upload a multi-sheet drawing PDF | E14: Each sheet listed with its sheet number | F14: High | G14: Not started
A15: DRW-02 | B15: DrawLogix | C15: Upload CAD | D15: Upload a DWG or DXF | E15: Layers and entities read; opens in the viewer | F15: High | G15: Not started
... A43: PLT-08 | B43: Platform | C43: Blocked request | D43: Process an unclassified document | E43: Refused with a clear message, not silence | F43: High | G43: Not started

Sheet Test · Documents
A1: ‹ Contents
A3: ID | B3: Size band | C3: File used | D3: Size MB | E3: Pages | F3: Target sec | G3: Run 1 | H3: Run 2 | I3: Avg sec | J3: Tokens in | K3: Tokens out | L3: Result | M3: Tokens/page | N3: Tester | O3: Notes
A4: DOC-A1 | B4: < 0.5 MB | F4: 10 | I4: =IF(COUNT(G4:H4)=0,"",AVERAGE(G4:H4)) | L4: =IF(I4="","Not started",IF(I4<=F4,"Pass","Fail")) -> Not started | M4: =IF(OR(E4="",J4=""),"",(J4+K4)/E4)
A5: DOC-A2 | B5: < 0.5 MB | F5: 10 | I5: =IF(COUNT(G5:H5)=0,"",AVERAGE(G5:H5)) | L5: =IF(I5="","Not started",IF(I5<=F5,"Pass","Fail")) -> Not started | M5: =IF(OR(E5="",J5=""),"",(J5+K5)/E5)
A6: DOC-A3 | B6: < 0.5 MB | F6: 10 | I6: =IF(COUNT(G6:H6)=0,"",AVERAGE(G6:H6)) | L6: =IF(I6="","Not started",IF(I6<=F6,"Pass","Fail")) -> Not started | M6: =IF(OR(E6="",J6=""),"",(J6+K6)/E6)
A7: DOC-B1 | B7: 0.5 – 2 MB | F7: 30 | I7: =IF(COUNT(G7:H7)=0,"",AVERAGE(G7:H7)) | L7: =IF(I7="","Not started",IF(I7<=F7,"Pass","Fail")) -> Not started | M7: =IF(OR(E7="",J7=""),"",(J7+K7)/E7)
A8: DOC-B2 | B8: 0.5 – 2 MB | F8: 30 | I8: =IF(COUNT(G8:H8)=0,"",AVERAGE(G8:H8)) | L8: =IF(I8="","Not started",IF(I8<=F8,"Pass","Fail")) -> Not started | M8: =IF(OR(E8="",J8=""),"",(J8+K8)/E8)
A9: DOC-B3 | B9: 0.5 – 2 MB | F9: 30 | I9: =IF(COUNT(G9:H9)=0,"",AVERAGE(G9:H9)) | L9: =IF(I9="","Not started",IF(I9<=F9,"Pass","Fail")) -> Not started | M9: =IF(OR(E9="",J9=""),"",(J9+K9)/E9)
A10: DOC-C1 | B10: 2 – 8 MB | F10: 90 | I10: =IF(COUNT(G10:H10)=0,"",AVERAGE(G10:H10)) | L10: =IF(I10="","Not started",IF(I10<=F10,"Pass","Fail")) -> Not started | M10: =IF(OR(E10="",J10=""),"",(J10+K10)/E10)
A11: DOC-C2 | B11: 2 – 8 MB | F11: 90 | I11: =IF(COUNT(G11:H11)=0,"",AVERAGE(G11:H11)) | L11: =IF(I11="","Not started",IF(I11<=F11,"Pass","Fail")) -> Not started | M11: =IF(OR(E11="",J11=""),"",(J11+K11)/E11)
A12: DOC-C3 | B12: 2 – 8 MB | F12: 90 | I12: =IF(COUNT(G12:H12)=0,"",AVERAGE(G12:H12)) | L12: =IF(I12="","Not started",IF(I12<=F12,"Pass","Fail")) -> Not started | M12: =IF(OR(E12="",J12=""),"",(J12+K12)/E12)
A13: DOC-D1 | B13: 8 – 32 MB | F13: 300 | I13: =IF(COUNT(G13:H13)=0,"",AVERAGE(G13:H13)) | L13: =IF(I13="","Not started",IF(I13<=F13,"Pass","Fail")) -> Not started | M13: =IF(OR(E13="",J13=""),"",(J13+K13)/E13)
A14: DOC-D2 | B14: 8 – 32 MB | F14: 300 | I14: =IF(COUNT(G14:H14)=0,"",AVERAGE(G14:H14)) | L14: =IF(I14="","Not started",IF(I14<=F14,"Pass","Fail")) -> Not started | M14: =IF(OR(E14="",J14=""),"",(J14+K14)/E14)
A15: DOC-D3 | B15: 8 – 32 MB | F15: 300 | I15: =IF(COUNT(G15:H15)=0,"",AVERAGE(G15:H15)) | L15: =IF(I15="","Not started",IF(I15<=F15,"Pass","Fail")) -> Not started | M15: =IF(OR(E15="",J15=""),"",(J15+K15)/E15)
... A18: DOC-E3 | B18: 32 MB + | F18: 600 | I18: =IF(COUNT(G18:H18)=0,"",AVERAGE(G18:H18)) | L18: =IF(I18="","Not started",IF(I18<=F18,"Pass","Fail")) -> Not started | M18: =IF(OR(E18="",J18=""),"",(J18+K18)/E18)
A20: Today's live figures get FASTER as files get bigger — 3.9 s under 0.5 MB but 2.4 s above 32 MB. That is not credible; understand why before treating any of it as a baseline. Tokens per page is the column to watch: if it is flat across every band, the counter is still a placeholder.

Sheet Test · Drawings
A1: ‹ Contents
A3: ID | B3: Complexity | C3: Drawing used | D3: Format | E3: Sheets | F3: Layers | G3: Entities | H3: Size MB | I3: Target sec | J3: Run 1 | K3: Run 2 | L3: Avg sec | M3: Result | N3: Tokens | O3: Tester | P3: Notes
A4: DRW-SIM1 | B4: Simple | I4: 30 | L4: =IF(COUNT(J4:K4)=0,"",AVERAGE(J4:K4)) | M4: =IF(L4="","Not started",IF(L4<=I4,"Pass","Fail")) -> Not started | P4: Single sheet, one discipline, under 500 entities
A5: DRW-SIM2 | B5: Simple | I5: 30 | L5: =IF(COUNT(J5:K5)=0,"",AVERAGE(J5:K5)) | M5: =IF(L5="","Not started",IF(L5<=I5,"Pass","Fail")) -> Not started
A6: DRW-SIM3 | B6: Simple | I6: 30 | L6: =IF(COUNT(J6:K6)=0,"",AVERAGE(J6:K6)) | M6: =IF(L6="","Not started",IF(L6<=I6,"Pass","Fail")) -> Not started
A7: DRW-MED1 | B7: Medium | I7: 120 | L7: =IF(COUNT(J7:K7)=0,"",AVERAGE(J7:K7)) | M7: =IF(L7="","Not started",IF(L7<=I7,"Pass","Fail")) -> Not started | P7: 2–5 sheets, 2–3 disciplines, 500–5,000 entities
A8: DRW-MED2 | B8: Medium | I8: 120 | L8: =IF(COUNT(J8:K8)=0,"",AVERAGE(J8:K8)) | M8: =IF(L8="","Not started",IF(L8<=I8,"Pass","Fail")) -> Not started
A9: DRW-MED3 | B9: Medium | I9: 120 | L9: =IF(COUNT(J9:K9)=0,"",AVERAGE(J9:K9)) | M9: =IF(L9="","Not started",IF(L9<=I9,"Pass","Fail")) -> Not started
A10: DRW-CPX1 | B10: Complex | I10: 600 | L10: =IF(COUNT(J10:K10)=0,"",AVERAGE(J10:K10)) | M10: =IF(L10="","Not started",IF(L10<=I10,"Pass","Fail")) -> Not started | P10: 6+ sheets, multi-discipline, over 5,000 entities
A11: DRW-CPX2 | B11: Complex | I11: 600 | L11: =IF(COUNT(J11:K11)=0,"",AVERAGE(J11:K11)) | M11: =IF(L11="","Not started",IF(L11<=I11,"Pass","Fail")) -> Not started
A12: DRW-CPX3 | B12: Complex | I12: 600 | L12: =IF(COUNT(J12:K12)=0,"",AVERAGE(J12:K12)) | M12: =IF(L12="","Not started",IF(L12<=I12,"Pass","Fail")) -> Not started
A13: DRW-SCN1 | B13: Scanned | I13: 300 | L13: =IF(COUNT(J13:K13)=0,"",AVERAGE(J13:K13)) | M13: =IF(L13="","Not started",IF(L13<=I13,"Pass","Fail")) -> Not started | P13: Raster PDF with no vector data at all
A14: DRW-SCN2 | B14: Scanned | I14: 300 | L14: =IF(COUNT(J14:K14)=0,"",AVERAGE(J14:K14)) | M14: =IF(L14="","Not started",IF(L14<=I14,"Pass","Fail")) -> Not started
A15: DRW-SCN3 | B15: Scanned | I15: 300 | L15: =IF(COUNT(J15:K15)=0,"",AVERAGE(J15:K15)) | M15: =IF(L15="","Not started",IF(L15<=I15,"Pass","Fail")) -> Not started
A17: Record entities and layers for every drawing — they turn "it was slow" into "it was slow at 40,000 entities". The live system returns no entity or layer count at all today, so read them from the CAD file by hand.

Sheet Test · Tokens
A1: ‹ Contents
A3: ID | B3: Step | C3: What it does | D3: Runs | E3: Avg in | F3: Avg out | G3: Avg total | H3: Target | I3: Result | J3: Cost / run | K3: Worst run | L3: Tester | M3: Notes
A4: TOK-01 | B4: Reading documents | C4: Sorts and splits the uploaded tender pack | G4: =IF(COUNT(E4:F4)=0,"",E4+F4) | H4: 4000 | I4: =IF(G4="","Not started",IF(G4<=H4,"Pass","Fail")) -> Not started | J4: =IF(G4="","",G4/1000*0.129)
A5: TOK-02 | B5: Tender reading | C5: Pulls summary, dates and requirements | G5: =IF(COUNT(E5:F5)=0,"",E5+F5) | H5: 8000 | I5: =IF(G5="","Not started",IF(G5<=H5,"Pass","Fail")) -> Not started | J5: =IF(G5="","",G5/1000*0.129)
A6: TOK-03 | B6: Bid / no-bid decision | C6: Recommends whether to pursue | G6: =IF(COUNT(E6:F6)=0,"",E6+F6) | H6: 3000 | I6: =IF(G6="","Not started",IF(G6<=H6,"Pass","Fail")) -> Not started | J6: =IF(G6="","",G6/1000*0.129)
A7: TOK-04 | B7: Specification reading | C7: Extracts clauses from the specification | G7: =IF(COUNT(E7:F7)=0,"",E7+F7) | H7: 8000 | I7: =IF(G7="","Not started",IF(G7<=H7,"Pass","Fail")) -> Not started | J7: =IF(G7="","",G7/1000*0.129)
A8: TOK-05 | B8: Drawing indexing | C8: Catalogues each drawing sheet | G8: =IF(COUNT(E8:F8)=0,"",E8+F8) | H8: 3000 | I8: =IF(G8="","Not started",IF(G8<=H8,"Pass","Fail")) -> Not started | J8: =IF(G8="","",G8/1000*0.129)
A9: TOK-06 | B9: Drawing take-off | C9: Measures quantities off the drawings | G9: =IF(COUNT(E9:F9)=0,"",E9+F9) | H9: 12000 | I9: =IF(G9="","Not started",IF(G9<=H9,"Pass","Fail")) -> Not started | J9: =IF(G9="","",G9/1000*0.129)
A10: TOK-07 | B10: Bill of quantities | C10: Turns measurements into bill lines | G10: =IF(COUNT(E10:F10)=0,"",E10+F10) | H10: 6000 | I10: =IF(G10="","Not started",IF(G10<=H10,"Pass","Fail")) -> Not started | J10: =IF(G10="","",G10/1000*0.129)
A11: TOK-08 | B11: Pricing | C11: Applies rates to the bill lines | G11: =IF(COUNT(E11:F11)=0,"",E11+F11) | H11: 4000 | I11: =IF(G11="","Not started",IF(G11<=H11,"Pass","Fail")) -> Not started | J11: =IF(G11="","",G11/1000*0.129)
A12: TOK-09 | B12: Compliance checks | C12: Checks the bid against requirements | G12: =IF(COUNT(E12:F12)=0,"",E12+F12) | H12: 6000 | I12: =IF(G12="","Not started",IF(G12<=H12,"Pass","Fail")) -> Not started | J12: =IF(G12="","",G12/1000*0.129)
A13: TOK-10 | B13: Risk assessment | C13: Flags risks on the bid | G13: =IF(COUNT(E13:F13)=0,"",E13+F13) | H13: 4000 | I13: =IF(G13="","Not started",IF(G13<=H13,"Pass","Fail")) -> Not started | J13: =IF(G13="","",G13/1000*0.129)
A14: TOK-11 | B14: Programme / schedule | C14: Builds the works programme | G14: =IF(COUNT(E14:F14)=0,"",E14+F14) | H14: 6000 | I14: =IF(G14="","Not started",IF(G14<=H14,"Pass","Fail")) -> Not started | J14: =IF(G14="","",G14/1000*0.129)
A15: TOK-12 | B15: Procurement packages | C15: Groups bill lines into packages | G15: =IF(COUNT(E15:F15)=0,"",E15+F15) | H15: 4000 | I15: =IF(G15="","Not started",IF(G15<=H15,"Pass","Fail")) -> Not started | J15: =IF(G15="","",G15/1000*0.129)
... A20: TOK-17 | B20: Copilot answers | C20: Answers questions people ask | G20: =IF(COUNT(E20:F20)=0,"",E20+F20) | H20: 3000 | I20: =IF(G20="","Not started",IF(G20<=H20,"Pass","Fail")) -> Not started | J20: =IF(G20="","",G20/1000*0.129)
B21: TOTAL — one full bid | G21: =SUM(G4:G20) -> 0 | H21: =SUM(H4:H20) -> 97000 | J21: =SUM(J4:J20) -> 0
A23: That total is the number the manager wants: the token cost of one complete bid, to multiply by bids per year. Targets in column H are first guesses — replace them once one real bid has been measured.

Sheet Test · Accuracy
A1: ‹ Contents
A3: ID | B3: What is extracted | C3: Test set used | D3: In truth | E3: Found | F3: Correct | G3: Wrong | H3: Missed | I3: Precision | J3: Recall | K3: F1 | L3: Target recall | M3: Result | N3: Notes
A4: ACC-01 | B4: Tender requirements | C4: One real tender, marked by an estimator | I4: =IF(E4=0,"",F4/E4) | J4: =IF(D4=0,"",F4/D4) | K4: =IF(OR(I4="",J4="",I4+J4=0),"",2*I4*J4/(I4+J4)) -> #VALUE! | L4: 0.9 | M4: =IF(J4="","Not started",IF(J4>=L4,"Pass","Fail")) -> Not started
A5: ACC-02 | B5: Submission dates and format | C5: Same tender | I5: =IF(E5=0,"",F5/E5) | J5: =IF(D5=0,"",F5/D5) | K5: =IF(OR(I5="",J5="",I5+J5=0),"",2*I5*J5/(I5+J5)) -> #VALUE! | L5: 0.95 | M5: =IF(J5="","Not started",IF(J5>=L5,"Pass","Fail")) -> Not started
A6: ACC-03 | B6: Specification clauses | C6: One spec, clauses marked by hand | I6: =IF(E6=0,"",F6/E6) | J6: =IF(D6=0,"",F6/D6) | K6: =IF(OR(I6="",J6="",I6+J6=0),"",2*I6*J6/(I6+J6)) -> #VALUE! | L6: 0.9 | M6: =IF(J6="","Not started",IF(J6>=L6,"Pass","Fail")) -> Not started
A7: ACC-04 | B7: Document classification | C7: 50 mixed documents, labelled by hand | I7: =IF(E7=0,"",F7/E7) | J7: =IF(D7=0,"",F7/D7) | K7: =IF(OR(I7="",J7="",I7+J7=0),"",2*I7*J7/(I7+J7)) -> #VALUE! | L7: 0.95 | M7: =IF(J7="","Not started",IF(J7>=L7,"Pass","Fail")) -> Not started
A8: ACC-05 | B8: Drawing sheet index | C8: One drawing set, sheets listed by hand | I8: =IF(E8=0,"",F8/E8) | J8: =IF(D8=0,"",F8/D8) | K8: =IF(OR(I8="",J8="",I8+J8=0),"",2*I8*J8/(I8+J8)) -> #VALUE! | L8: 0.95 | M8: =IF(J8="","Not started",IF(J8>=L8,"Pass","Fail")) -> Not started
A9: ACC-06 | B9: Drawing measurements | C9: One drawing measured by a QS | I9: =IF(E9=0,"",F9/E9) | J9: =IF(D9=0,"",F9/D9) | K9: =IF(OR(I9="",J9="",I9+J9=0),"",2*I9*J9/(I9+J9)) -> #VALUE! | L9: 0.9 | M9: =IF(J9="","Not started",IF(J9>=L9,"Pass","Fail")) -> Not started
A10: ACC-07 | B10: BOQ line generation | C10: Bill produced by hand from the same drawings | I10: =IF(E10=0,"",F10/E10) | J10: =IF(D10=0,"",F10/D10) | K10: =IF(OR(I10="",J10="",I10+J10=0),"",2*I10*J10/(I10+J10)) -> #VALUE! | L10: 0.85 | M10: =IF(J10="","Not started",IF(J10>=L10,"Pass","Fail")) -> Not started
A11: ACC-08 | B11: Rate matching | C11: Bill priced by hand from the same library | I11: =IF(E11=0,"",F11/E11) | J11: =IF(D11=0,"",F11/D11) | K11: =IF(OR(I11="",J11="",I11+J11=0),"",2*I11*J11/(I11+J11)) -> #VALUE! | L11: 0.9 | M11: =IF(J11="","Not started",IF(J11>=L11,"Pass","Fail")) -> Not started
A12: ACC-09 | B12: Programme activities | C12: Programme built by hand from the same bill | I12: =IF(E12=0,"",F12/E12) | J12: =IF(D12=0,"",F12/D12) | K12: =IF(OR(I12="",J12="",I12+J12=0),"",2*I12*J12/(I12+J12)) -> #VALUE! | L12: 0.8 | M12: =IF(J12="","Not started",IF(J12>=L12,"Pass","Fail")) -> Not started
A13: ACC-10 | B13: Risk identification | C13: Risks listed by a bid manager | I13: =IF(E13=0,"",F13/E13) | J13: =IF(D13=0,"",F13/D13) | K13: =IF(OR(I13="",J13="",I13+J13=0),"",2*I13*J13/(I13+J13)) -> #VALUE! | L13: 0.75 | M13: =IF(J13="","Not started",IF(J13>=L13,"Pass","Fail")) -> Not started
A15: What the columns mean
B16: In truth | C16: How many there actually are, counted by a person.
B17: Found | C17: How many the system returned.
B18: Correct | C18: How many of those found were right.
B19: Precision | C19: Of what it found, how much was right.
B20: Recall | C20: Of what was there, how much it found.
B21: F1 | C21: The two combined into one number.
B23: Recall matters more than precision. A requirement the system invents gets caught in review; one it misses ends up in a contract nobody priced.

Sheet Targets
A1: ‹ Contents
A3: Measure | B3: Proposed target | C3: Today | D3: Basis
A4: Document < 0.5 MB | B4: 10 sec | C4: 3.9 sec | D4: Comfortably met.
A5: Document 0.5 – 2 MB | B5: 30 sec | C5: 10.5 sec | D5: Met.
A6: Document 2 – 8 MB | B6: 90 sec | C6: 9.4 sec | D6: Met.
A7: Document 8 – 32 MB | B7: 300 sec | C7: 5.4 sec | D7: Suspiciously fast — verify.
A8: Document 32 MB + | B8: 600 sec | C8: 2.4 sec | D8: Faster than a small file. Not credible.
A9: Drawing — simple | B9: 30 sec | C9: not measured | D9: No timing recorded today.
A10: Drawing — medium | B10: 120 sec | C10: not measured | D10: No timing recorded today.
A11: Drawing — complex | B11: 600 sec | C11: not measured | D11: No timing recorded today.
A12: Queue wait, any job | B12: 60 sec | C12: up to 37 hrs | D12: Worst case is the programme step.
A13: Tokens, one full bid | B13: 90,000 | C13: not measured | D13: Sum of the step targets.
A14: Cost, one full bid | B14: $11.61 | C14: $0.56 placeholder | D14: 90,000 tokens at $0.129 / 1k.
... A18: Functional tests passing | B18: 100% of High | C18: not measured | D18: High priority must all pass.

Sheet Test data needed
A1: ‹ Contents
A3: ID | B3: What is needed | C3: Why | D3: Priority | E3: Owner | F3: Ready by | G3: Notes
A4: TD-01 | B4: One complete real tender pack | C4: Drives almost every functional and accuracy test | D4: High
A5: TD-02 | B5: The priced bill that tender produced | C5: Answer key for BOQ and rate accuracy | D5: High
A6: TD-03 | B6: 3 documents at each of the 5 size bands | C6: 15 files for the document sheet | D6: High
A7: TD-04 | B7: 3 each simple / medium / complex / scanned drawings | C7: 12 files for the drawing sheet | D7: High
A8: TD-05 | B8: A drawing measured by a QS | C8: Answer key for measurement accuracy | D8: High
A9: TD-06 | B9: A specification with clauses marked up | C9: Answer key for clause extraction | D9: Medium
A10: TD-07 | B10: 50 mixed documents labelled by type | C10: Answer key for classification | D10: Medium
A11: TD-08 | B11: A programme built by hand from the same bill | C11: Answer key for scheduling | D11: Medium
A12: TD-09 | B12: A second revision of one drawing | C12: Revision compare and the stale cascade | D12: Medium
A13: TD-10 | B13: Test accounts for each role | C13: Permission and review-queue tests | D13: High

Sheet Glossary
A1: ‹ Contents
A2: What the terms mean
A4: Term | B4: What it means
A5: AI request | B5: One call from the platform to the AI, for one step of one bid.
A6: Job | B6: One unit of background work. A job may make one AI request, or none.
A7: Blocked by privacy rule | B7: The platform refused to send data to the AI because it was unclassified, and unclassified is treated as confidential. Working as designed.
A8: Queue wait | B8: How long a job sat waiting before it started running.
A9: Waiting for approval | B9: The AI produced a suggestion. Nothing joins the bid until a named person confirms it.
A10: Repeat work reused | B10: When the platform reuses an answer it already produced. Currently switched off.
A11: System error | B11: A genuine fault, as opposed to a deliberate refusal.
A12: Tokens | B12: The unit the AI charges in. Roughly three-quarters of a word each.
A13: Usage figures | B13: How much AI capacity a request consumed. Currently a fixed placeholder, so it cannot be used for cost.
A14: Precision | B14: Of what the system found, how much was actually right.
A15: Recall | B15: Of what was really there, how much the system found.
